questdb_ilp_client/LineTcpSender.py
questdb_ilp_client/__init__.py
questdb_ilp_client-0.1.0.dist-info/LICENSE
questdb_ilp_client-0.1.0.dist-info/WHEEL
questdb_ilp_client-0.1.0.dist-info/METADATA
questdb_ilp_client-0.1.0.dist-info/RECORD
