Metadata-Version: 2.1
Name: questdb-ilp-client
Version: 0.1.0
Summary: A Python3 API for ingesting data into QuestDB through the InfluxDB Line Protocol.
Home-page: https://github.com/nsco1/py-questdb-client
License: Apache-2.0
Keywords: QuestDB,ILP,database,time series
Author: Nathan Scott
Author-email: nathan@nathanscott.co.uk
Requires-Python: >=3.9,<4.0
Classifier: License :: OSI Approved :: Apache Software License
Classifier: Programming Language :: Python :: 3
Classifier: Programming Language :: Python :: 3.10
Classifier: Programming Language :: Python :: 3.9
Project-URL: Documentation, https://github.com/nsco1/py-questdb-client/blob/main/README.md
Project-URL: Repository, https://github.com/nsco1/py-questdb-client
